aws_lambda_invoker/__init__.py
aws_lambda_invoker/ag_lambda_invoker.py
aws_lambda_invoker/lambda_invoker.py
aws_lambda_invoker-0.0.2.dist-info/METADATA
aws_lambda_invoker-0.0.2.dist-info/WHEEL
aws_lambda_invoker-0.0.2.dist-info/top_level.txt
aws_lambda_invoker-0.0.2.dist-info/RECORD
