Metadata-Version: 2.4
Name: aws_lambda_invoker
Version: 0.0.2
Summary: AWS Lambda invoker
Author-email: SirPaulO <me@sirpauloliver.com>
License: MIT License
Project-URL: Homepage, https://github.com/SirPaulO/aws_lambda_invoker
Project-URL: Bug Tracker, https://github.com/SirPaulO/aws_lambda_invoker/issues
Project-URL: Repository, https://github.com/SirPaulO/aws_lambda_invoker.git
Keywords: aws,lambda,invoke,sqs,sns,eventbridge,apigateway
Classifier: Programming Language :: Python :: 3
Classifier: License :: OSI Approved :: MIT License
Classifier: Operating System :: OS Independent
Requires-Python: >=3.7
Requires-Dist: boto3~=1.39.13
Requires-Dist: orjson~=3.11.1
